odoo/addons/mail_force_email_notification/README.rst
odoo/addons/mail_force_email_notification/__init__.py
odoo/addons/mail_force_email_notification/__manifest__.py
odoo/addons/mail_force_email_notification/i18n/it.po
odoo/addons/mail_force_email_notification/i18n/mail_force_email_notification.pot
odoo/addons/mail_force_email_notification/models/__init__.py
odoo/addons/mail_force_email_notification/models/mail_thread.py
odoo/addons/mail_force_email_notification/readme/CONTRIBUTORS.md
odoo/addons/mail_force_email_notification/readme/CREDITS.md
odoo/addons/mail_force_email_notification/readme/DESCRIPTION.md
odoo/addons/mail_force_email_notification/readme/USAGE.md
odoo/addons/mail_force_email_notification/readme/newsfragments/.gitkeep
odoo/addons/mail_force_email_notification/static/description/icon.png
odoo/addons/mail_force_email_notification/static/description/index.html
odoo/addons/mail_force_email_notification/tests/__init__.py
odoo/addons/mail_force_email_notification/tests/test_mail_thread.py
odoo_addon_mail_force_email_notification-18.0.1.0.0.4.dist-info/METADATA
odoo_addon_mail_force_email_notification-18.0.1.0.0.4.dist-info/WHEEL
odoo_addon_mail_force_email_notification-18.0.1.0.0.4.dist-info/top_level.txt
odoo_addon_mail_force_email_notification-18.0.1.0.0.4.dist-info/RECORD
