Metadata-Version: 2.1
Name: odoo-addon-mail_force_email_notification
Version: 18.0.1.0.0.4
Requires-Python: >=3.10
Requires-Dist: odoo==18.0.*
Summary: Context key to define notifications to be sent by emaildefined by force_notification_by_email context key
Home-page: https://github.com/OCA/mail
License: AGPL-3
Author: Camptocamp, Odoo Community Association (OCA)
Author-email: support@odoo-community.org
Classifier: Programming Language :: Python
Classifier: Framework :: Odoo
Classifier: Framework :: Odoo :: 18.0
Classifier: License :: OSI Approved :: GNU Affero General Public License v3
